{"status":0,"runtime_ms":3580,"counters":{"PERF_COUNT_HW_CPU_CYCLES":12294775001,"PERF_COUNT_HW_INSTRUCTIONS":28151257340,"PERF_COUNT_HW_CACHE_REFERENCES":602749937,"PERF_COUNT_HW_CACHE_MISSES":286960282,"PERF_COUNT_HW_BRANCH_INSTRUCTIONS":6054269958,"PERF_COUNT_HW_BRANCH_MISSES":27078346,"PERF_COUNT_HW_BUS_CYCLES":10552222888,"PERF_COUNT_HW_REF_CPU_CYCLES":10552105696,"PERF_COUNT_SW_TASK_CLOCK":3623675385,"PERF_COUNT_SW_PAGE_FAULTS":297210},"energy_samples":[{"duration_ms":1000,"energy":[{"pkg":15.677734375,"pp0":9.16387939453125,"pp1":0,"dram":0}]},{"duration_ms":1000,"energy":[{"pkg":16.36871337890625,"pp0":9.617431640625,"pp1":0,"dram":0}]},{"duration_ms":1000,"energy":[{"pkg":16.666259765625,"pp0":9.9490966796875,"pp1":0,"dram":0}]},{"duration_ms":579,"energy":[{"pkg":8.22418212890625,"pp0":4.1876220703125,"pp1":0,"dram":0}]}],"process":{"samples":[{"duration_ms":144,"private_memory":78400,"shared_memory":1212,"swapped_memory":0},{"duration_ms":103,"private_memory":197712,"shared_memory":1208,"swapped_memory":0},{"duration_ms":104,"private_memory":346988,"shared_memory":1208,"swapped_memory":0},{"duration_ms":105,"private_memory":724028,"shared_memory":1208,"swapped_memory":0},{"duration_ms":106,"private_memory":913268,"shared_memory":1208,"swapped_memory":0},{"duration_ms":107,"private_memory":965652,"shared_memory":2920,"swapped_memory":0},{"duration_ms":107,"private_memory":983668,"shared_memory":2920,"swapped_memory":0},{"duration_ms":108,"private_memory":964308,"shared_memory":1208,"swapped_memory":0},{"duration_ms":107,"private_memory":1014764,"shared_memory":2920,"swapped_memory":0},{"duration_ms":108,"private_memory":1033196,"shared_memory":2920,"swapped_memory":0},{"duration_ms":107,"private_memory":1002896,"shared_memory":1208,"swapped_memory":0},{"duration_ms":107,"private_memory":1020160,"shared_memory":1208,"swapped_memory":0},{"duration_ms":107,"private_memory":1064540,"shared_memory":2920,"swapped_memory":0},{"duration_ms":107,"private_memory":1050784,"shared_memory":1208,"swapped_memory":0},{"duration_ms":108,"private_memory":1107432,"shared_memory":2920,"swapped_memory":0},{"duration_ms":107,"private_memory":1124068,"shared_memory":2920,"swapped_memory":0},{"duration_ms":107,"private_memory":1132260,"shared_memory":2920,"swapped_memory":0},{"duration_ms":107,"private_memory":1132260,"shared_memory":2920,"swapped_memory":0},{"duration_ms":108,"private_memory":1143524,"shared_memory":2920,"swapped_memory":0},{"duration_ms":107,"private_memory":1155356,"shared_memory":2920,"swapped_memory":0},{"duration_ms":108,"private_memory":1178072,"shared_memory":2920,"swapped_memory":0},{"duration_ms":107,"private_memory":1190360,"shared_memory":2920,"swapped_memory":0},{"duration_ms":107,"private_memory":1195992,"shared_memory":2920,"swapped_memory":0},{"duration_ms":109,"private_memory":1219412,"shared_memory":2920,"swapped_memory":0},{"duration_ms":108,"private_memory":1233936,"shared_memory":2920,"swapped_memory":0},{"duration_ms":108,"private_memory":1219692,"shared_memory":1208,"swapped_memory":0},{"duration_ms":108,"private_memory":1264840,"shared_memory":2920,"swapped_memory":0},{"duration_ms":108,"private_memory":1281352,"shared_memory":2920,"swapped_memory":0},{"duration_ms":109,"private_memory":1308152,"shared_memory":2920,"swapped_memory":0},{"duration_ms":107,"private_memory":1281340,"shared_memory":2984,"swapped_memory":0},{"duration_ms":107,"private_memory":1281340,"shared_memory":2984,"swapped_memory":0},{"duration_ms":111,"private_memory":1281340,"shared_memory":2984,"swapped_memory":0}],"cpu_count":16,"avg_cpu":94.2}}
{"status":0,"runtime_ms":3779,"counters":{"PERF_COUNT_HW_CPU_CYCLES":12885868982,"PERF_COUNT_HW_INSTRUCTIONS":28608203713,"PERF_COUNT_HW_CACHE_REFERENCES":590627465,"PERF_COUNT_HW_CACHE_MISSES":280479811,"PERF_COUNT_HW_BRANCH_INSTRUCTIONS":6144235886,"PERF_COUNT_HW_BRANCH_MISSES":27329269,"PERF_COUNT_HW_BUS_CYCLES":11167018048,"PERF_COUNT_HW_REF_CPU_CYCLES":11166933460,"PERF_COUNT_SW_TASK_CLOCK":3834647256,"PERF_COUNT_SW_PAGE_FAULTS":296627},"energy_samples":[{"duration_ms":1000,"energy":[{"pkg":15.43548583984375,"pp0":8.9212646484375,"pp1":0,"dram":0}]},{"duration_ms":1000,"energy":[{"pkg":15.4444580078125,"pp0":8.6754150390625,"pp1":0,"dram":0}]},{"duration_ms":1000,"energy":[{"pkg":17.082763671875,"pp0":10.56146240234375,"pp1":0,"dram":0}]},{"duration_ms":779,"energy":[{"pkg":11.16461181640625,"pp0":5.6676025390625,"pp1":0,"dram":0}]}],"process":{"samples":[{"duration_ms":144,"private_memory":73044,"shared_memory":2180,"swapped_memory":0},{"duration_ms":103,"private_memory":192328,"shared_memory":1300,"swapped_memory":0},{"duration_ms":104,"private_memory":300404,"shared_memory":1300,"swapped_memory":0},{"duration_ms":105,"private_memory":680548,"shared_memory":1300,"swapped_memory":0},{"duration_ms":106,"private_memory":911256,"shared_memory":1300,"swapped_memory":0},{"duration_ms":106,"private_memory":927896,"shared_memory":1300,"swapped_memory":0},{"duration_ms":107,"private_memory":981648,"shared_memory":3040,"swapped_memory":0},{"duration_ms":106,"private_memory":959080,"shared_memory":1300,"swapped_memory":0},{"duration_ms":106,"private_memory":976124,"shared_memory":1300,"swapped_memory":0},{"duration_ms":107,"private_memory":1029128,"shared_memory":3040,"swapped_memory":0},{"duration_ms":107,"private_memory":1033224,"shared_memory":3040,"swapped_memory":0},{"duration_ms":107,"private_memory":1008760,"shared_memory":1300,"swapped_memory":0},{"duration_ms":107,"private_memory":1061524,"shared_memory":3040,"swapped_memory":0},{"duration_ms":107,"private_memory":1073732,"shared_memory":3040,"swapped_memory":0},{"duration_ms":107,"private_memory":1057628,"shared_memory":1300,"swapped_memory":0},{"duration_ms":107,"private_memory":1107712,"shared_memory":3040,"swapped_memory":0},{"duration_ms":107,"private_memory":1124096,"shared_memory":3040,"swapped_memory":0},{"duration_ms":108,"private_memory":1132288,"shared_memory":3040,"swapped_memory":0},{"duration_ms":107,"private_memory":1132288,"shared_memory":3040,"swapped_memory":0},{"duration_ms":107,"private_memory":1099428,"shared_memory":1300,"swapped_memory":0},{"duration_ms":107,"private_memory":1143552,"shared_memory":3040,"swapped_memory":0},{"duration_ms":107,"private_memory":1126256,"shared_memory":1300,"swapped_memory":0},{"duration_ms":108,"private_memory":1178100,"shared_memory":3040,"swapped_memory":0},{"duration_ms":107,"private_memory":1190388,"shared_memory":3040,"swapped_memory":0},{"duration_ms":108,"private_memory":1201424,"shared_memory":3040,"swapped_memory":0},{"duration_ms":107,"private_memory":1219472,"shared_memory":3040,"swapped_memory":0},{"duration_ms":107,"private_memory":1235200,"shared_memory":2788,"swapped_memory":0},{"duration_ms":108,"private_memory":1256676,"shared_memory":3040,"swapped_memory":0},{"duration_ms":109,"private_memory":1276820,"shared_memory":3040,"swapped_memory":0},{"duration_ms":107,"private_memory":1281380,"shared_memory":3040,"swapped_memory":0},{"duration_ms":108,"private_memory":1314152,"shared_memory":3040,"swapped_memory":0},{"duration_ms":107,"private_memory":1281368,"shared_memory":3100,"swapped_memory":0},{"duration_ms":107,"private_memory":1281368,"shared_memory":3100,"swapped_memory":0},{"duration_ms":111,"private_memory":1281368,"shared_memory":3100,"swapped_memory":0}],"cpu_count":16,"avg_cpu":94.5}}
{"status":0,"runtime_ms":3558,"counters":{"PERF_COUNT_HW_CPU_CYCLES":12249618894,"PERF_COUNT_HW_INSTRUCTIONS":28511677774,"PERF_COUNT_HW_CACHE_REFERENCES":607051485,"PERF_COUNT_HW_CACHE_MISSES":290517678,"PERF_COUNT_HW_BRANCH_INSTRUCTIONS":6127220040,"PERF_COUNT_HW_BRANCH_MISSES":27193560,"PERF_COUNT_HW_BUS_CYCLES":10496676464,"PERF_COUNT_HW_REF_CPU_CYCLES":10496569304,"PERF_COUNT_SW_TASK_CLOCK":3604787294,"PERF_COUNT_SW_PAGE_FAULTS":295028},"energy_samples":[{"duration_ms":1000,"energy":[{"pkg":15.68719482421875,"pp0":9.1400146484375,"pp1":0,"dram":0}]},{"duration_ms":1000,"energy":[{"pkg":16.5828857421875,"pp0":9.825439453125,"pp1":0,"dram":0}]},{"duration_ms":1000,"energy":[{"pkg":16.47607421875,"pp0":9.7225341796875,"pp1":0,"dram":0}]},{"duration_ms":557,"energy":[{"pkg":8.09100341796875,"pp0":4.15277099609375,"pp1":0,"dram":0}]}],"process":{"samples":[{"duration_ms":145,"private_memory":71832,"shared_memory":1280,"swapped_memory":0},{"duration_ms":103,"private_memory":193272,"shared_memory":1280,"swapped_memory":0},{"duration_ms":104,"private_memory":330480,"shared_memory":1280,"swapped_memory":0},{"duration_ms":105,"private_memory":708180,"shared_memory":1280,"swapped_memory":0},{"duration_ms":106,"private_memory":913316,"shared_memory":1280,"swapped_memory":0},{"duration_ms":106,"private_memory":932960,"shared_memory":1280,"swapped_memory":0},{"duration_ms":106,"private_memory":983724,"shared_memory":3056,"swapped_memory":0},{"duration_ms":106,"private_memory":998248,"shared_memory":3056,"swapped_memory":0},{"duration_ms":107,"private_memory":1021064,"shared_memory":3056,"swapped_memory":0},{"duration_ms":107,"private_memory":1033352,"shared_memory":3056,"swapped_memory":0},{"duration_ms":107,"private_memory":1006144,"shared_memory":1280,"swapped_memory":0},{"duration_ms":107,"private_memory":1062100,"shared_memory":3056,"swapped_memory":0},{"duration_ms":107,"private_memory":1042940,"shared_memory":1280,"swapped_memory":0},{"duration_ms":108,"private_memory":1095452,"shared_memory":3056,"swapped_memory":0},{"duration_ms":107,"private_memory":1107740,"shared_memory":3056,"swapped_memory":0},{"duration_ms":108,"private_memory":1129612,"shared_memory":3056,"swapped_memory":0},{"duration_ms":107,"private_memory":1132316,"shared_memory":3056,"swapped_memory":0},{"duration_ms":107,"private_memory":1132316,"shared_memory":3056,"swapped_memory":0},{"duration_ms":107,"private_memory":1143580,"shared_memory":3056,"swapped_memory":0},{"duration_ms":107,"private_memory":1162264,"shared_memory":3056,"swapped_memory":0},{"duration_ms":108,"private_memory":1186320,"shared_memory":3056,"swapped_memory":0},{"duration_ms":107,"private_memory":1190416,"shared_memory":3056,"swapped_memory":0},{"duration_ms":107,"private_memory":1171300,"shared_memory":1280,"swapped_memory":0},{"duration_ms":107,"private_memory":1219468,"shared_memory":3056,"swapped_memory":0},{"duration_ms":107,"private_memory":1202404,"shared_memory":1280,"swapped_memory":0},{"duration_ms":108,"private_memory":1256704,"shared_memory":3056,"swapped_memory":0},{"duration_ms":109,"private_memory":1277068,"shared_memory":3056,"swapped_memory":0},{"duration_ms":108,"private_memory":1281408,"shared_memory":3056,"swapped_memory":0},{"duration_ms":108,"private_memory":1314180,"shared_memory":3056,"swapped_memory":0},{"duration_ms":107,"private_memory":1281408,"shared_memory":3168,"swapped_memory":0},{"duration_ms":107,"private_memory":1281408,"shared_memory":3168,"swapped_memory":0},{"duration_ms":110,"private_memory":1281408,"shared_memory":3168,"swapped_memory":0}],"cpu_count":16,"avg_cpu":94.5}}
{"status":0,"runtime_ms":3640,"counters":{"PERF_COUNT_HW_CPU_CYCLES":12408697006,"PERF_COUNT_HW_INSTRUCTIONS":28561989675,"PERF_COUNT_HW_CACHE_REFERENCES":610178178,"PERF_COUNT_HW_CACHE_MISSES":292460063,"PERF_COUNT_HW_BRANCH_INSTRUCTIONS":6135752673,"PERF_COUNT_HW_BRANCH_MISSES":27316139,"PERF_COUNT_HW_BUS_CYCLES":10755404252,"PERF_COUNT_HW_REF_CPU_CYCLES":10755296256,"PERF_COUNT_SW_TASK_CLOCK":3694083222,"PERF_COUNT_SW_PAGE_FAULTS":295375},"energy_samples":[{"duration_ms":1000,"energy":[{"pkg":15.72576904296875,"pp0":9.179931640625,"pp1":0,"dram":0}]},{"duration_ms":1000,"energy":[{"pkg":16.599365234375,"pp0":9.844482421875,"pp1":0,"dram":0}]},{"duration_ms":1000,"energy":[{"pkg":16.47601318359375,"pp0":9.7481689453125,"pp1":0,"dram":0}]},{"duration_ms":640,"energy":[{"pkg":8.692138671875,"pp0":4.31072998046875,"pp1":0,"dram":0}]}],"process":{"samples":[{"duration_ms":145,"private_memory":82548,"shared_memory":1320,"swapped_memory":0},{"duration_ms":104,"private_memory":198180,"shared_memory":1320,"swapped_memory":0},{"duration_ms":104,"private_memory":330536,"shared_memory":1320,"swapped_memory":0},{"duration_ms":106,"private_memory":702560,"shared_memory":1320,"swapped_memory":0},{"duration_ms":106,"private_memory":946092,"shared_memory":3100,"swapped_memory":0},{"duration_ms":106,"private_memory":932984,"shared_memory":1320,"swapped_memory":0},{"duration_ms":107,"private_memory":983752,"shared_memory":3100,"swapped_memory":0},{"duration_ms":107,"private_memory":965532,"shared_memory":1320,"swapped_memory":0},{"duration_ms":107,"private_memory":1020992,"shared_memory":3100,"swapped_memory":0},{"duration_ms":106,"private_memory":1033280,"shared_memory":3100,"swapped_memory":0},{"duration_ms":106,"private_memory":1006168,"shared_memory":1320,"swapped_memory":0},{"duration_ms":108,"private_memory":1062320,"shared_memory":3100,"swapped_memory":0},{"duration_ms":108,"private_memory":1076860,"shared_memory":3100,"swapped_memory":0},{"duration_ms":108,"private_memory":1062608,"shared_memory":1320,"swapped_memory":0},{"duration_ms":108,"private_memory":1107768,"shared_memory":3100,"swapped_memory":0},{"duration_ms":108,"private_memory":1132344,"shared_memory":3100,"swapped_memory":0},{"duration_ms":107,"private_memory":1132344,"shared_memory":3100,"swapped_memory":0},{"duration_ms":107,"private_memory":1132344,"shared_memory":3100,"swapped_memory":0},{"duration_ms":107,"private_memory":1143704,"shared_memory":3100,"swapped_memory":0},{"duration_ms":107,"private_memory":1130360,"shared_memory":1320,"swapped_memory":0},{"duration_ms":108,"private_memory":1186352,"shared_memory":3100,"swapped_memory":0},{"duration_ms":107,"private_memory":1190448,"shared_memory":3100,"swapped_memory":0},{"duration_ms":108,"private_memory":1171052,"shared_memory":1320,"swapped_memory":0},{"duration_ms":107,"private_memory":1219496,"shared_memory":3100,"swapped_memory":0},{"duration_ms":107,"private_memory":1203524,"shared_memory":1320,"swapped_memory":0},{"duration_ms":108,"private_memory":1256732,"shared_memory":3100,"swapped_memory":0},{"duration_ms":108,"private_memory":1278516,"shared_memory":3100,"swapped_memory":0},{"duration_ms":108,"private_memory":1281436,"shared_memory":3100,"swapped_memory":0},{"duration_ms":108,"private_memory":1248564,"shared_memory":1320,"swapped_memory":0},{"duration_ms":107,"private_memory":1281424,"shared_memory":3160,"swapped_memory":0},{"duration_ms":107,"private_memory":1281424,"shared_memory":3160,"swapped_memory":0},{"duration_ms":111,"private_memory":1281424,"shared_memory":3160,"swapped_memory":0},{"duration_ms":110,"private_memory":1281424,"shared_memory":3160,"swapped_memory":0}],"cpu_count":16,"avg_cpu":94.4}}
{"status":0,"runtime_ms":3569,"counters":{"PERF_COUNT_HW_CPU_CYCLES":12312094310,"PERF_COUNT_HW_INSTRUCTIONS":28530497894,"PERF_COUNT_HW_CACHE_REFERENCES":608581778,"PERF_COUNT_HW_CACHE_MISSES":292171231,"PERF_COUNT_HW_BRANCH_INSTRUCTIONS":6130765734,"PERF_COUNT_HW_BRANCH_MISSES":27290352,"PERF_COUNT_HW_BUS_CYCLES":10467722972,"PERF_COUNT_HW_REF_CPU_CYCLES":10467609428,"PERF_COUNT_SW_TASK_CLOCK":3594565709,"PERF_COUNT_SW_PAGE_FAULTS":296010},"energy_samples":[{"duration_ms":1000,"energy":[{"pkg":15.899658203125,"pp0":9.3314208984375,"pp1":0,"dram":0}]},{"duration_ms":1000,"energy":[{"pkg":16.72332763671875,"pp0":9.96026611328125,"pp1":0,"dram":0}]},{"duration_ms":1000,"energy":[{"pkg":16.43499755859375,"pp0":9.73004150390625,"pp1":0,"dram":0}]},{"duration_ms":569,"energy":[{"pkg":8.17779541015625,"pp0":4.2154541015625,"pp1":0,"dram":0}]}],"process":{"samples":[{"duration_ms":144,"private_memory":82980,"shared_memory":1284,"swapped_memory":0},{"duration_ms":103,"private_memory":209304,"shared_memory":1284,"swapped_memory":0},{"duration_ms":104,"private_memory":392996,"shared_memory":1284,"swapped_memory":0},{"duration_ms":106,"private_memory":758356,"shared_memory":1284,"swapped_memory":0},{"duration_ms":106,"private_memory":915700,"shared_memory":1284,"swapped_memory":0},{"duration_ms":107,"private_memory":934604,"shared_memory":1284,"swapped_memory":0},{"duration_ms":106,"private_memory":983792,"shared_memory":3064,"swapped_memory":0},{"duration_ms":107,"private_memory":966720,"shared_memory":1284,"swapped_memory":0},{"duration_ms":106,"private_memory":1021032,"shared_memory":3064,"swapped_memory":0},{"duration_ms":107,"private_memory":1033320,"shared_memory":3064,"swapped_memory":0},{"duration_ms":107,"private_memory":1007892,"shared_memory":1284,"swapped_memory":0},{"duration_ms":108,"private_memory":1062360,"shared_memory":3064,"swapped_memory":0},{"duration_ms":107,"private_memory":1076900,"shared_memory":3064,"swapped_memory":0},{"duration_ms":108,"private_memory":1099616,"shared_memory":3064,"swapped_memory":0},{"duration_ms":108,"private_memory":1107808,"shared_memory":3064,"swapped_memory":0},{"duration_ms":108,"private_memory":1132384,"shared_memory":3064,"swapped_memory":0},{"duration_ms":107,"private_memory":1132384,"shared_memory":3064,"swapped_memory":0},{"duration_ms":108,"private_memory":1135456,"shared_memory":3064,"swapped_memory":0},{"duration_ms":107,"private_memory":1113728,"shared_memory":1284,"swapped_memory":0},{"duration_ms":108,"private_memory":1131500,"shared_memory":1284,"swapped_memory":0},{"duration_ms":108,"private_memory":1186440,"shared_memory":3064,"swapped_memory":0},{"duration_ms":107,"private_memory":1190536,"shared_memory":3064,"swapped_memory":0},{"duration_ms":107,"private_memory":1172648,"shared_memory":1284,"swapped_memory":0},{"duration_ms":107,"private_memory":1219536,"shared_memory":3064,"swapped_memory":0},{"duration_ms":107,"private_memory":1205468,"shared_memory":1284,"swapped_memory":0},{"duration_ms":108,"private_memory":1256772,"shared_memory":3064,"swapped_memory":0},{"duration_ms":108,"private_memory":1280652,"shared_memory":3064,"swapped_memory":0},{"duration_ms":108,"private_memory":1281476,"shared_memory":3064,"swapped_memory":0},{"duration_ms":107,"private_memory":1248600,"shared_memory":1284,"swapped_memory":0},{"duration_ms":107,"private_memory":1281464,"shared_memory":3124,"swapped_memory":0},{"duration_ms":107,"private_memory":1281464,"shared_memory":3124,"swapped_memory":0},{"duration_ms":111,"private_memory":1281464,"shared_memory":3124,"swapped_memory":0}],"cpu_count":16,"avg_cpu":93.3}}
{"status":0,"runtime_ms":3635,"counters":{"PERF_COUNT_HW_CPU_CYCLES":12503435796,"PERF_COUNT_HW_INSTRUCTIONS":28574302775,"PERF_COUNT_HW_CACHE_REFERENCES":599242669,"PERF_COUNT_HW_CACHE_MISSES":284284484,"PERF_COUNT_HW_BRANCH_INSTRUCTIONS":6138417288,"PERF_COUNT_HW_BRANCH_MISSES":27237254,"PERF_COUNT_HW_BUS_CYCLES":10718737748,"PERF_COUNT_HW_REF_CPU_CYCLES":10718675960,"PERF_COUNT_SW_TASK_CLOCK":3681419702,"PERF_COUNT_SW_PAGE_FAULTS":295881},"energy_samples":[{"duration_ms":1000,"energy":[{"pkg":15.87451171875,"pp0":9.32666015625,"pp1":0,"dram":0}]},{"duration_ms":1000,"energy":[{"pkg":16.5794677734375,"pp0":9.83441162109375,"pp1":0,"dram":0}]},{"duration_ms":1000,"energy":[{"pkg":16.09527587890625,"pp0":9.47076416015625,"pp1":0,"dram":0}]},{"duration_ms":634,"energy":[{"pkg":9.11444091796875,"pp0":4.701171875,"pp1":0,"dram":0}]}],"process":{"samples":[{"duration_ms":144,"private_memory":82320,"shared_memory":1220,"swapped_memory":0},{"duration_ms":103,"private_memory":202440,"shared_memory":1220,"swapped_memory":0},{"duration_ms":104,"private_memory":367800,"shared_memory":1220,"swapped_memory":0},{"duration_ms":105,"private_memory":745196,"shared_memory":1220,"swapped_memory":0},{"duration_ms":106,"private_memory":915148,"shared_memory":1220,"swapped_memory":0},{"duration_ms":107,"private_memory":934080,"shared_memory":1220,"swapped_memory":0},{"duration_ms":106,"private_memory":983784,"shared_memory":2992,"swapped_memory":0},{"duration_ms":106,"private_memory":967108,"shared_memory":1220,"swapped_memory":0},{"duration_ms":106,"private_memory":1021024,"shared_memory":2992,"swapped_memory":0},{"duration_ms":106,"private_memory":1033312,"shared_memory":2992,"swapped_memory":0},{"duration_ms":107,"private_memory":1008028,"shared_memory":1220,"swapped_memory":0},{"duration_ms":108,"private_memory":1062352,"shared_memory":2992,"swapped_memory":0},{"duration_ms":106,"private_memory":1076892,"shared_memory":2992,"swapped_memory":0},{"duration_ms":108,"private_memory":1099608,"shared_memory":2992,"swapped_memory":0},{"duration_ms":108,"private_memory":1107800,"shared_memory":2992,"swapped_memory":0},{"duration_ms":108,"private_memory":1132376,"shared_memory":2992,"swapped_memory":0},{"duration_ms":107,"private_memory":1132376,"shared_memory":2992,"swapped_memory":0},{"duration_ms":108,"private_memory":1135448,"shared_memory":2992,"swapped_memory":0},{"duration_ms":107,"private_memory":1113728,"shared_memory":1220,"swapped_memory":0},{"duration_ms":107,"private_memory":1132732,"shared_memory":1220,"swapped_memory":0},{"duration_ms":108,"private_memory":1186380,"shared_memory":2992,"swapped_memory":0},{"duration_ms":107,"private_memory":1190476,"shared_memory":2992,"swapped_memory":0},{"duration_ms":107,"private_memory":1170540,"shared_memory":1220,"swapped_memory":0},{"duration_ms":107,"private_memory":1219528,"shared_memory":2992,"swapped_memory":0},{"duration_ms":107,"private_memory":1234052,"shared_memory":2992,"swapped_memory":0},{"duration_ms":108,"private_memory":1219800,"shared_memory":1220,"swapped_memory":0},{"duration_ms":107,"private_memory":1264956,"shared_memory":2992,"swapped_memory":0},{"duration_ms":108,"private_memory":1281340,"shared_memory":2992,"swapped_memory":0},{"duration_ms":108,"private_memory":1281468,"shared_memory":2992,"swapped_memory":0},{"duration_ms":108,"private_memory":1281456,"shared_memory":2992,"swapped_memory":0},{"duration_ms":107,"private_memory":1281456,"shared_memory":3116,"swapped_memory":0},{"duration_ms":110,"private_memory":1281456,"shared_memory":3116,"swapped_memory":0},{"duration_ms":109,"private_memory":1281456,"shared_memory":3116,"swapped_memory":0}],"cpu_count":16,"avg_cpu":94.1}}
{"status":0,"runtime_ms":3578,"counters":{"PERF_COUNT_HW_CPU_CYCLES":12247609611,"PERF_COUNT_HW_INSTRUCTIONS":28504799798,"PERF_COUNT_HW_CACHE_REFERENCES":606293271,"PERF_COUNT_HW_CACHE_MISSES":288667363,"PERF_COUNT_HW_BRANCH_INSTRUCTIONS":6125770202,"PERF_COUNT_HW_BRANCH_MISSES":27301752,"PERF_COUNT_HW_BUS_CYCLES":10549514400,"PERF_COUNT_HW_REF_CPU_CYCLES":10549396600,"PERF_COUNT_SW_TASK_CLOCK":3622673470,"PERF_COUNT_SW_PAGE_FAULTS":294215},"energy_samples":[{"duration_ms":1000,"energy":[{"pkg":15.73583984375,"pp0":9.1298828125,"pp1":0,"dram":0}]},{"duration_ms":1000,"energy":[{"pkg":16.5982666015625,"pp0":9.83062744140625,"pp1":0,"dram":0}]},{"duration_ms":1000,"energy":[{"pkg":16.463134765625,"pp0":9.74334716796875,"pp1":0,"dram":0}]},{"duration_ms":578,"energy":[{"pkg":8.19915771484375,"pp0":4.1881103515625,"pp1":0,"dram":0}]}],"process":{"samples":[{"duration_ms":144,"private_memory":76812,"shared_memory":1272,"swapped_memory":0},{"duration_ms":103,"private_memory":191916,"shared_memory":1272,"swapped_memory":0},{"duration_ms":103,"private_memory":313076,"shared_memory":1272,"swapped_memory":0},{"duration_ms":105,"private_memory":690908,"shared_memory":1272,"swapped_memory":0},{"duration_ms":106,"private_memory":946020,"shared_memory":2996,"swapped_memory":0},{"duration_ms":106,"private_memory":932924,"shared_memory":1272,"swapped_memory":0},{"duration_ms":107,"private_memory":983680,"shared_memory":2996,"swapped_memory":0},{"duration_ms":106,"private_memory":999356,"shared_memory":2996,"swapped_memory":0},{"duration_ms":107,"private_memory":1020920,"shared_memory":2996,"swapped_memory":0},{"duration_ms":106,"private_memory":1033208,"shared_memory":2996,"swapped_memory":0},{"duration_ms":107,"private_memory":1008368,"shared_memory":1272,"swapped_memory":0},{"duration_ms":108,"private_memory":1062368,"shared_memory":2996,"swapped_memory":0},{"duration_ms":107,"private_memory":1076788,"shared_memory":2996,"swapped_memory":0},{"duration_ms":108,"private_memory":1099504,"shared_memory":2996,"swapped_memory":0},{"duration_ms":108,"private_memory":1107696,"shared_memory":2996,"swapped_memory":0},{"duration_ms":108,"private_memory":1132272,"shared_memory":2996,"swapped_memory":0},{"duration_ms":106,"private_memory":1132272,"shared_memory":2996,"swapped_memory":0},{"duration_ms":107,"private_memory":1100436,"shared_memory":1272,"swapped_memory":0},{"duration_ms":107,"private_memory":1143536,"shared_memory":2996,"swapped_memory":0},{"duration_ms":107,"private_memory":1129516,"shared_memory":1272,"swapped_memory":0},{"duration_ms":108,"private_memory":1185468,"shared_memory":2996,"swapped_memory":0},{"duration_ms":107,"private_memory":1190372,"shared_memory":2996,"swapped_memory":0},{"duration_ms":108,"private_memory":1170000,"shared_memory":1272,"swapped_memory":0},{"duration_ms":107,"private_memory":1219424,"shared_memory":2996,"swapped_memory":0},{"duration_ms":107,"private_memory":1202916,"shared_memory":1272,"swapped_memory":0},{"duration_ms":107,"private_memory":1256660,"shared_memory":2996,"swapped_memory":0},{"duration_ms":109,"private_memory":1277412,"shared_memory":2996,"swapped_memory":0},{"duration_ms":107,"private_memory":1281364,"shared_memory":2996,"swapped_memory":0},{"duration_ms":108,"private_memory":1314136,"shared_memory":2996,"swapped_memory":0},{"duration_ms":107,"private_memory":1281352,"shared_memory":3056,"swapped_memory":0},{"duration_ms":107,"private_memory":1281352,"shared_memory":3056,"swapped_memory":0},{"duration_ms":113,"private_memory":1281352,"shared_memory":3056,"swapped_memory":0}],"cpu_count":16,"avg_cpu":94.5}}
{"status":0,"runtime_ms":3622,"counters":{"PERF_COUNT_HW_CPU_CYCLES":12324292272,"PERF_COUNT_HW_INSTRUCTIONS":28559030148,"PERF_COUNT_HW_CACHE_REFERENCES":606974158,"PERF_COUNT_HW_CACHE_MISSES":290453951,"PERF_COUNT_HW_BRANCH_INSTRUCTIONS":6134877705,"PERF_COUNT_HW_BRANCH_MISSES":27245367,"PERF_COUNT_HW_BUS_CYCLES":10659936092,"PERF_COUNT_HW_REF_CPU_CYCLES":10659879548,"PERF_COUNT_SW_TASK_CLOCK":3660167430,"PERF_COUNT_SW_PAGE_FAULTS":296421},"energy_samples":[{"duration_ms":1000,"energy":[{"pkg":16.0008544921875,"pp0":9.4229736328125,"pp1":0,"dram":0}]},{"duration_ms":1000,"energy":[{"pkg":16.426025390625,"pp0":9.70709228515625,"pp1":0,"dram":0}]},{"duration_ms":1000,"energy":[{"pkg":16.20269775390625,"pp0":9.5301513671875,"pp1":0,"dram":0}]},{"duration_ms":621,"energy":[{"pkg":8.84991455078125,"pp0":4.5228271484375,"pp1":0,"dram":0}]}],"process":{"samples":[{"duration_ms":149,"private_memory":78792,"shared_memory":1252,"swapped_memory":0},{"duration_ms":103,"private_memory":205116,"shared_memory":1252,"swapped_memory":0},{"duration_ms":104,"private_memory":375912,"shared_memory":1252,"swapped_memory":0},{"duration_ms":106,"private_memory":753584,"shared_memory":1252,"swapped_memory":0},{"duration_ms":106,"private_memory":915876,"shared_memory":1252,"swapped_memory":0},{"duration_ms":106,"private_memory":934964,"shared_memory":1252,"swapped_memory":0},{"duration_ms":106,"private_memory":983680,"shared_memory":2964,"swapped_memory":0},{"duration_ms":107,"private_memory":967848,"shared_memory":1252,"swapped_memory":0},{"duration_ms":107,"private_memory":1020920,"shared_memory":2964,"swapped_memory":0},{"duration_ms":106,"private_memory":1033208,"shared_memory":2964,"swapped_memory":0},{"duration_ms":107,"private_memory":1009404,"shared_memory":1252,"swapped_memory":0},{"duration_ms":108,"private_memory":1062300,"shared_memory":2964,"swapped_memory":0},{"duration_ms":107,"private_memory":1076788,"shared_memory":2964,"swapped_memory":0},{"duration_ms":107,"private_memory":1062548,"shared_memory":1252,"swapped_memory":0},{"duration_ms":107,"private_memory":1107696,"shared_memory":2964,"swapped_memory":0},{"duration_ms":108,"private_memory":1129888,"shared_memory":2964,"swapped_memory":0},{"duration_ms":107,"private_memory":1132272,"shared_memory":2964,"swapped_memory":0},{"duration_ms":107,"private_memory":1132272,"shared_memory":2964,"swapped_memory":0},{"duration_ms":108,"private_memory":1143536,"shared_memory":2964,"swapped_memory":0},{"duration_ms":107,"private_memory":1162120,"shared_memory":2964,"swapped_memory":0},{"duration_ms":108,"private_memory":1186276,"shared_memory":2964,"swapped_memory":0},{"duration_ms":107,"private_memory":1190372,"shared_memory":2964,"swapped_memory":0},{"duration_ms":108,"private_memory":1170444,"shared_memory":1252,"swapped_memory":0},{"duration_ms":107,"private_memory":1219424,"shared_memory":2964,"swapped_memory":0},{"duration_ms":107,"private_memory":1203184,"shared_memory":1252,"swapped_memory":0},{"duration_ms":107,"private_memory":1256660,"shared_memory":2964,"swapped_memory":0},{"duration_ms":109,"private_memory":1231992,"shared_memory":1252,"swapped_memory":0},{"duration_ms":111,"private_memory":1281236,"shared_memory":2964,"swapped_memory":0},{"duration_ms":109,"private_memory":1301628,"shared_memory":2964,"swapped_memory":0},{"duration_ms":108,"private_memory":1281352,"shared_memory":3024,"swapped_memory":0},{"duration_ms":108,"private_memory":1281352,"shared_memory":3024,"swapped_memory":0},{"duration_ms":111,"private_memory":1281352,"shared_memory":3024,"swapped_memory":0},{"duration_ms":108,"private_memory":1215720,"shared_memory":1312,"swapped_memory":0}],"cpu_count":16,"avg_cpu":93.8}}
{"status":0,"runtime_ms":3552,"counters":{"PERF_COUNT_HW_CPU_CYCLES":12242600110,"PERF_COUNT_HW_INSTRUCTIONS":28516160803,"PERF_COUNT_HW_CACHE_REFERENCES":609105727,"PERF_COUNT_HW_CACHE_MISSES":292617692,"PERF_COUNT_HW_BRANCH_INSTRUCTIONS":6128213951,"PERF_COUNT_HW_BRANCH_MISSES":27305176,"PERF_COUNT_HW_BUS_CYCLES":10435436652,"PERF_COUNT_HW_REF_CPU_CYCLES":10435330632,"PERF_COUNT_SW_TASK_CLOCK":3584090195,"PERF_COUNT_SW_PAGE_FAULTS":295002},"energy_samples":[{"duration_ms":1000,"energy":[{"pkg":15.948486328125,"pp0":9.38897705078125,"pp1":0,"dram":0}]},{"duration_ms":1000,"energy":[{"pkg":16.7078857421875,"pp0":9.947265625,"pp1":0,"dram":0}]},{"duration_ms":1000,"energy":[{"pkg":16.3668212890625,"pp0":9.666259765625,"pp1":0,"dram":0}]},{"duration_ms":551,"energy":[{"pkg":7.99554443359375,"pp0":4.16387939453125,"pp1":0,"dram":0}]}],"process":{"samples":[{"duration_ms":147,"private_memory":78292,"shared_memory":1304,"swapped_memory":0},{"duration_ms":103,"private_memory":206728,"shared_memory":1304,"swapped_memory":0},{"duration_ms":104,"private_memory":375004,"shared_memory":1304,"swapped_memory":0},{"duration_ms":105,"private_memory":758844,"shared_memory":1304,"swapped_memory":0},{"duration_ms":106,"private_memory":915764,"shared_memory":1304,"swapped_memory":0},{"duration_ms":106,"private_memory":933872,"shared_memory":1304,"swapped_memory":0},{"duration_ms":106,"private_memory":983708,"shared_memory":3004,"swapped_memory":0},{"duration_ms":106,"private_memory":966784,"shared_memory":1304,"swapped_memory":0},{"duration_ms":107,"private_memory":1020948,"shared_memory":3004,"swapped_memory":0},{"duration_ms":106,"private_memory":1033236,"shared_memory":3004,"swapped_memory":0},{"duration_ms":106,"private_memory":1007544,"shared_memory":1304,"swapped_memory":0},{"duration_ms":108,"private_memory":1062276,"shared_memory":3004,"swapped_memory":0},{"duration_ms":106,"private_memory":1076816,"shared_memory":3004,"swapped_memory":0},{"duration_ms":107,"private_memory":1099332,"shared_memory":3004,"swapped_memory":0},{"duration_ms":108,"private_memory":1107724,"shared_memory":3004,"swapped_memory":0},{"duration_ms":108,"private_memory":1132300,"shared_memory":3004,"swapped_memory":0},{"duration_ms":107,"private_memory":1132300,"shared_memory":3004,"swapped_memory":0},{"duration_ms":107,"private_memory":1135372,"shared_memory":3004,"swapped_memory":0},{"duration_ms":107,"private_memory":1113660,"shared_memory":1304,"swapped_memory":0},{"duration_ms":107,"private_memory":1133304,"shared_memory":1304,"swapped_memory":0},{"duration_ms":108,"private_memory":1186304,"shared_memory":3004,"swapped_memory":0},{"duration_ms":107,"private_memory":1190400,"shared_memory":3004,"swapped_memory":0},{"duration_ms":107,"private_memory":1173048,"shared_memory":1304,"swapped_memory":0},{"duration_ms":107,"private_memory":1219452,"shared_memory":3004,"swapped_memory":0},{"duration_ms":107,"private_memory":1205692,"shared_memory":1304,"swapped_memory":0},{"duration_ms":109,"private_memory":1256688,"shared_memory":3004,"swapped_memory":0},{"duration_ms":108,"private_memory":1280704,"shared_memory":3004,"swapped_memory":0},{"duration_ms":108,"private_memory":1281392,"shared_memory":3004,"swapped_memory":0},{"duration_ms":108,"private_memory":1281380,"shared_memory":3004,"swapped_memory":0},{"duration_ms":107,"private_memory":1281380,"shared_memory":3064,"swapped_memory":0},{"duration_ms":109,"private_memory":1281380,"shared_memory":3064,"swapped_memory":0},{"duration_ms":113,"private_memory":1281380,"shared_memory":3064,"swapped_memory":0}],"cpu_count":16,"avg_cpu":93.9}}
{"status":0,"runtime_ms":3567,"counters":{"PERF_COUNT_HW_CPU_CYCLES":12301240886,"PERF_COUNT_HW_INSTRUCTIONS":28499986134,"PERF_COUNT_HW_CACHE_REFERENCES":610318087,"PERF_COUNT_HW_CACHE_MISSES":293084434,"PERF_COUNT_HW_BRANCH_INSTRUCTIONS":6124230622,"PERF_COUNT_HW_BRANCH_MISSES":27232009,"PERF_COUNT_HW_BUS_CYCLES":10450631864,"PERF_COUNT_HW_REF_CPU_CYCLES":10450516192,"PERF_COUNT_SW_TASK_CLOCK":3588714017,"PERF_COUNT_SW_PAGE_FAULTS":294140},"energy_samples":[{"duration_ms":1000,"energy":[{"pkg":15.9232177734375,"pp0":9.37774658203125,"pp1":0,"dram":0}]},{"duration_ms":1000,"energy":[{"pkg":16.65899658203125,"pp0":9.84625244140625,"pp1":0,"dram":0}]},{"duration_ms":1000,"energy":[{"pkg":16.62091064453125,"pp0":9.797607421875,"pp1":0,"dram":0}]},{"duration_ms":567,"energy":[{"pkg":8.17071533203125,"pp0":4.1590576171875,"pp1":0,"dram":0}]}],"process":{"samples":[{"duration_ms":146,"private_memory":83680,"shared_memory":1264,"swapped_memory":0},{"duration_ms":103,"private_memory":209080,"shared_memory":1264,"swapped_memory":0},{"duration_ms":104,"private_memory":391792,"shared_memory":1264,"swapped_memory":0},{"duration_ms":106,"private_memory":762432,"shared_memory":1264,"swapped_memory":0},{"duration_ms":106,"private_memory":917180,"shared_memory":1264,"swapped_memory":0},{"duration_ms":107,"private_memory":935252,"shared_memory":1264,"swapped_memory":0},{"duration_ms":106,"private_memory":983684,"shared_memory":2984,"swapped_memory":0},{"duration_ms":106,"private_memory":966628,"shared_memory":1264,"swapped_memory":0},{"duration_ms":107,"private_memory":1020924,"shared_memory":2984,"swapped_memory":0},{"duration_ms":107,"private_memory":1033212,"shared_memory":2984,"swapped_memory":0},{"duration_ms":107,"private_memory":1007144,"shared_memory":1264,"swapped_memory":0},{"duration_ms":108,"private_memory":1062252,"shared_memory":2984,"swapped_memory":0},{"duration_ms":108,"private_memory":1076792,"shared_memory":2984,"swapped_memory":0},{"duration_ms":107,"private_memory":1062552,"shared_memory":1264,"swapped_memory":0},{"duration_ms":108,"private_memory":1107700,"shared_memory":2984,"swapped_memory":0},{"duration_ms":108,"private_memory":1132276,"shared_memory":2984,"swapped_memory":0},{"duration_ms":107,"private_memory":1132276,"shared_memory":2984,"swapped_memory":0},{"duration_ms":107,"private_memory":1099416,"shared_memory":1264,"swapped_memory":0},{"duration_ms":107,"private_memory":1143540,"shared_memory":2984,"swapped_memory":0},{"duration_ms":107,"private_memory":1129380,"shared_memory":1264,"swapped_memory":0},{"duration_ms":109,"private_memory":1186408,"shared_memory":2984,"swapped_memory":0},{"duration_ms":107,"private_memory":1190504,"shared_memory":2984,"swapped_memory":0},{"duration_ms":108,"private_memory":1170136,"shared_memory":1264,"swapped_memory":0},{"duration_ms":107,"private_memory":1219428,"shared_memory":2984,"swapped_memory":0},{"duration_ms":107,"private_memory":1202920,"shared_memory":1264,"swapped_memory":0},{"duration_ms":107,"private_memory":1256664,"shared_memory":2984,"swapped_memory":0},{"duration_ms":109,"private_memory":1276524,"shared_memory":2984,"swapped_memory":0},{"duration_ms":107,"private_memory":1281368,"shared_memory":2984,"swapped_memory":0},{"duration_ms":108,"private_memory":1314140,"shared_memory":2984,"swapped_memory":0},{"duration_ms":107,"private_memory":1281356,"shared_memory":3044,"swapped_memory":0},{"duration_ms":107,"private_memory":1281356,"shared_memory":3044,"swapped_memory":0},{"duration_ms":110,"private_memory":1281356,"shared_memory":3044,"swapped_memory":0}],"cpu_count":16,"avg_cpu":93.4}}
